{
  "product_id": "",
  "product_name": "McCol 70 WP",
  "product_image": "images/McCol_70_WP.jpg",
  "medicine_name": "",
  "category_name": "",
  "description": "",
  "application_rates": "",
  "frequency_of_use": "",
  "side_effect": "",
  "crops_pests": "",
  "crops": "",
  "pest": "",
  "symptoms": "",
  "causes": "",
  "product_tags": [],
  "product_price": "",
  "reg_no": "",
  "serial_no": "",
  "product_url": "",
  "origin": "",
  "isActive": "false",
  "Stocks": "",
  "extraction_date": "2025-10-15T00:00:00"
}
